MANIFEST.in
README.md
setup.cfg
setup.py
metaschool/__init__.py
metaschool/_version.py
metaschool/gym_taskset.py
metaschool/utils.py
metaschool.egg-info/PKG-INFO
metaschool.egg-info/SOURCES.txt
metaschool.egg-info/dependency_links.txt
metaschool.egg-info/requires.txt
metaschool.egg-info/top_level.txt
metaschool/wrappers/__init__.py
metaschool/wrappers/reward_scaler.py
tests/__init__.py