Metadata-Version: 2.1
Name: metaschool
Version: 0.0.1
Summary: Description of my super metaschool.
Home-page: https://learnables.github.com/metaschool
Author: Seb Arnold
Author-email: smr.arnold@gmail.com
License: License :: OSI Approved :: Apache Software License
Download-URL: https://github.com/learnables/metaschool/archive/0.0.1.zip
Platform: UNKNOWN
